{
  "db_name": "PostgreSQL",
  "query": "\n        SELECT\n            e.*,\n            p.priority,\n            o.id AS occurrence_id,\n            o.starts_at,\n            array_agg(l.local_event_id) as \"linked: Vec<Option<i32>>\",\n            o.from_rrule\n        FROM\n            events AS e\n        INNER JOIN\n            ics_sources AS s\n            ON e.event_source_id = s.id\n            AND (s.user_id = $1 OR s.is_public)\n        INNER JOIN\n            event_occurrences AS o\n            ON o.event_id = e.id\n        INNER JOIN\n            ics_source_priorities AS p\n            ON p.user_id = $1\n            AND p.ics_source_id = s.id\n            -- min_priority is null or (source_in_calendar and event_priority_override >= min_priority) or source_priority >= min_priority\n            AND ($4::integer IS NULL OR (p.priority IS NOT NULL AND COALESCE(NULLIF(e.priority_override, 0), $6) >= $4) OR COALESCE(NULLIF(p.priority, 0), $6) >= $4)\n            -- max_priority is null or (source_in_calendar and event_priority_override <= max_priority) and source_priority <= max_priority\n            AND ($5::integer IS NULL OR (p.priority IS NOT NULL AND COALESCE(NULLIF(e.priority_override, 0), $6) <= $5) AND COALESCE(NULLIF(p.priority, 0), $6) <= $5)\n        LEFT JOIN\n            remote_local_link AS l\n            ON o.id = l.remote_occurrence_id\n        WHERE\n            ($2::bigint IS NULL OR o.starts_at + COALESCE(e.duration, 0) > $2::bigint)\n            AND ($3::bigint IS NULL OR o.starts_at < $3)\n            AND ($7::text IS NULL OR e.summary LIKE $7)\n            --AND ($8::text[] IS NULL OR tag.tag = ANY($8))\n            --AND ($9::text[] IS NULL OR tag IS NULL OR (\n            --    SELECT tag.tag\n            --    FROM event_tags AS tag\n            --    WHERE tag.remote_event_id = e.id\n            --    AND tag.tag = ANY($9)\n            --) IS NULL)\n        GROUP BY\n            e.id, p.priority, o.starts_at, o.from_rrule, o.id\n        ORDER BY\n            o.starts_at;\n        ",
  "describe": {
    "columns": [
      {
        "ordinal": 0,
        "name": "id",
        "type_info": "Int4"
      },
      {
        "ordinal": 1,
        "name": "event_source_id",
        "type_info": "Int4"
      },
      {
        "ordinal": 2,
        "name": "dt_stamp",
        "type_info": "Int8"
      },
      {
        "ordinal": 3,
        "name": "duration",
        "type_info": "Int4"
      },
      {
        "ordinal": 4,
        "name": "summary",
        "type_info": "Text"
      },
      {
        "ordinal": 5,
        "name": "description",
        "type_info": "Text"
      },
      {
        "ordinal": 6,
        "name": "location",
        "type_info": "Text"
      },
      {
        "ordinal": 7,
        "name": "uid",
        "type_info": "Text"
      },
      {
        "ordinal": 8,
        "name": "rrule",
        "type_info": "Text"
      },
      {
        "ordinal": 9,
        "name": "all_day",
        "type_info": "Bool"
      },
      {
        "ordinal": 10,
        "name": "priority_override",
        "type_info": "Int4"
      },
      {
        "ordinal": 11,
        "name": "priority",
        "type_info": "Int4"
      },
      {
        "ordinal": 12,
        "name": "occurrence_id",
        "type_info": "Int4"
      },
      {
        "ordinal": 13,
        "name": "starts_at",
        "type_info": "Int8"
      },
      {
        "ordinal": 14,
        "name": "linked: Vec<Option<i32>>",
        "type_info": "Int4Array"
      },
      {
        "ordinal": 15,
        "name": "from_rrule",
        "type_info": "Bool"
      }
    ],
    "parameters": {
      "Left": [
        "Int4",
        "Int8",
        "Int8",
        "Int4",
        "Int4",
        "Int4",
        "Text"
      ]
    },
    "nullable": [
      false,
      false,
      true,
      true,
      false,
      true,
      true,
      false,
      true,
      false,
      true,
      false,
      false,
      false,
      null,
      false
    ]
  },
  "hash": "a5f9dad9ebe3aea2fb76c208316aac87c169cd516991832d415001db81929e29"
}
